_examples/__init__.py
examples/__init__.py
pyfileconf_datacode/__init__.py
pyfileconf_datacode/config.py
pyfileconf_datacode/dchooks.py
pyfileconf_datacode/dcopts.py
pyfileconf_datacode/deepdiff_patch.py
pyfileconf_datacode/model.py
pyfileconf_datacode/plugin.py
pyfileconf_datacode/reset.py
tests/__init__.py
tests/base.py
tests/test_hooks.py
tests/test_iter.py
tests/utils.py
tests/input_files/__init__.py
tests/input_files/example_config.py
tests/input_files/example_func.py
pyfileconf_datacode-0.1.6.dist-info/LICENSE.md
pyfileconf_datacode-0.1.6.dist-info/METADATA
pyfileconf_datacode-0.1.6.dist-info/WHEEL
pyfileconf_datacode-0.1.6.dist-info/entry_points.txt
pyfileconf_datacode-0.1.6.dist-info/top_level.txt
pyfileconf_datacode-0.1.6.dist-info/RECORD
