Metadata-Version: 2.1
Name: pyfileconf-datacode
Version: 0.1.6
Summary: pyfileconf plugin to support datacode operations
Home-page: https://github.com/nickderobertis/pyfileconf-datacode
Author: Nick DeRobertis
Author-email: whoopnip@gmail.com
License: MIT
Project-URL: Code, https://github.com/nickderobertis/pyfileconf-datacode
Project-URL: Documentation, https://nickderobertis.github.io/pyfileconf-datacode
Platform: UNKNOWN
Classifier: Development Status :: 3 - Alpha
Classifier: Intended Audience :: Developers
Classifier: Programming Language :: Python :: 3.6
Classifier: Programming Language :: Python :: 3.7
Requires-Dist: pyfileconf
Requires-Dist: datacode
